four/four_b.v
module four_b( reset,enable,d,q);
input d;
input enable;
input reset;
output reg q;
always @ ( *)
begin
if (reset) 
  q<= 0;
else
   q<=d;
end
endmodule

four/fourb_tb.v
module four_b_tb;
reg d;
reg enable;
reg reset;
wire q;
four_b uut (.reset(reset),. d(d),.enable(enable),.q(q));
initial
begin
 $dumpfile ("four_b.vcd");
$dumpvars(0,four_b_tb);
end
 initial
begin
reset = 1'b0;
#5 reset = 1'b1;
#5 reset = 1'b0;
#5 enable = 1'b1;
#5 d = 1'b0;
#5 d = 1'b1;
#5 d = 1'b0;
#5 d = 1'b1;
#100 $finish;
end
endmodule

four/four_b.vcd
$date
	Sat Feb 25 11:14:22 2023
$end
$version
	Icarus Verilog
$end
$timescale
	1s
$end
$scope module four_b_tb $end
$var wire 1 ! q $end
$var reg 1 " d $end
$var reg 1 # enable $end
$var reg 1 $ reset $end
$scope module uut $end
$var wire 1 " d $end
$var wire 1 # enable $end
$var wire 1 $ reset $end
$var reg 1 ! q $end
$upscope $end
$upscope $end
$enddefinitions $end
#0
$dumpvars
0$
x#
x"
x!
$end
#5
0!
1$
#10
x!
0$
#15
1#
#20
0!
0"
#25
1!
1"
#30
0!
0"
#35
1!
1"
